migretti/__init__.py
migretti/__main__.py
migretti/config.py
migretti/core.py
migretti/db.py
migretti/hooks.py
migretti/io_utils.py
migretti/logging_setup.py
migretti/prompt_cmd.py
migretti/seed.py
migretti/squash.py
migretti/ulid.py
migretti-0.9.5.dist-info/METADATA
migretti-0.9.5.dist-info/WHEEL
migretti-0.9.5.dist-info/entry_points.txt
migretti-0.9.5.dist-info/licenses/LICENSE
migretti-0.9.5.dist-info/RECORD
