Metadata-Version: 2.4
Name: migretti
Version: 0.9.5
Summary: A database migration tool for Python applications.
Project-URL: Homepage, https://github.com/rodmena-limited/migretti
Project-URL: Repository, https://github.com/rodmena-limited/migretti
Project-URL: Issues, https://github.com/rodmena-limited/migretti/issues
Author-email: Farshid <farshid@example.com>
License:                                  Apache License
License-File: LICENSE
Keywords: database,migration,sql
Classifier: Development Status :: 4 - Beta
Classifier: Intended Audience :: Developers
Classifier: License :: OSI Approved :: Apache Software License
Classifier: Operating System :: OS Independent
Classifier: Programming Language :: Python :: 3
Requires-Python: >=3.8
Requires-Dist: psycopg
Requires-Dist: python-dotenv
Requires-Dist: pyyaml
Requires-Dist: sqlparse
Provides-Extra: dev
Requires-Dist: build; extra == 'dev'
Requires-Dist: issuedb; extra == 'dev'
Requires-Dist: mypy; extra == 'dev'
Requires-Dist: pytest; extra == 'dev'
Requires-Dist: pytest-cov; extra == 'dev'
Requires-Dist: ruff; extra == 'dev'
Requires-Dist: types-pyyaml; extra == 'dev'
